nano_topology/__init__.py
nano_topology/graph_equivalence.py
nano_topology/nanosets.py
nanotopology-1.0.1.dist-info/LICENSE
nanotopology-1.0.1.dist-info/METADATA
nanotopology-1.0.1.dist-info/WHEEL
nanotopology-1.0.1.dist-info/top_level.txt
nanotopology-1.0.1.dist-info/RECORD
