Metadata-Version: 2.1
Name: nanotopology
Version: 1.0.1
Summary: A Python package to check the similarity of two graphs using nanotopology.
Home-page: https://github.com/J-Kiruthika/Nanotopology
Author: Kiruthika J
Author-email: kiruthika.17cs@kct.ac.in
License: MIT
Platform: UNKNOWN
Classifier: License :: OSI Approved :: MIT License
Classifier: Programming Language :: Python :: 3
Requires-Python: >=2.6
